pccalc/__init__.py
pccalc/calc.py
pccalc-0.0.1.dist-info/METADATA
pccalc-0.0.1.dist-info/WHEEL
pccalc-0.0.1.dist-info/top_level.txt
pccalc-0.0.1.dist-info/RECORD
